[
    {
        "id": "1",
        "videoUrl": "/service-videos/service5.mp4",
        "posterUrl": "/service-videos/service5-poster.webp",
        "title": "Hair Highlights"
    },
    {
        "id": "2",
        "videoUrl": "/service-videos/service2.mp4",
        "posterUrl": "/service-videos/service2-poster.webp",
        "title": "Bridal Hair Styling"
    },
    {
        "id": "3",
        "videoUrl": "/service-videos/service3.mp4",
        "posterUrl": "/service-videos/service3-poster.webp",
        "title": "Nail Art"
    },
    {
        "id": "4",
        "videoUrl": "/service-videos/service4.mp4",
        "posterUrl": "/service-videos/service4-poster.webp",
        "title": "Hair Extension"
    },
    {
        "id": "5",
        "videoUrl": "/service-videos/service1.mp4",
        "posterUrl": "/service-videos/service1-poster.webp",
        "title": "Skin Treatment"
    },
    {
        "id": "6",
        "videoUrl": "/service-videos/service6.mp4",
        "posterUrl": "/service-videos/service6-poster.webp",
        "title": "Festive Nails"
    },
    {
        "id": "7",
        "videoUrl": "/service-videos/service7.mp4",
        "posterUrl": "/service-videos/service7-poster.webp",
        "title": "Ombre Hair Color"
    }
]